pollination/custom_energy_sim/__init__.py
pollination/custom_energy_sim/entry.py
pollination_custom_energy_sim-0.3.25.dist-info/LICENSE
pollination_custom_energy_sim-0.3.25.dist-info/METADATA
pollination_custom_energy_sim-0.3.25.dist-info/WHEEL
pollination_custom_energy_sim-0.3.25.dist-info/top_level.txt
pollination_custom_energy_sim-0.3.25.dist-info/RECORD
