Metadata-Version: 2.1
Name: pollination-custom-energy-sim
Version: 0.3.25
Summary: Run an energy simulation with custom Simulation Parameters.
Home-page: https://github.com/pollination/custom-energy-sim
Author: ladybug-tools
Author-email: info@ladybug.tools
Maintainer: chris, ladybug-tools
Maintainer-email: chris@ladybug.tools, info@ladybug.tools
License: PolyForm Shield License 1.0.0, https://polyformproject.org/wp-content/uploads/2020/06/PolyForm-Shield-1.0.0.txt
Project-URL: icon, https://raw.githubusercontent.com/ladybug-tools/artwork/master/icons_components/honeybee/png/toopenstudio.png
Project-URL: docker, https://hub.docker.com/r/ladybugtools/honeybee-energy
Keywords: honeybee,energy,ladybug-tools,energyplus,openstudio,energy,custom-energy-sim
License-File: LICENSE
Requires-Dist: pollination-honeybee-energy>=0.7.16
Requires-Dist: pollination-alias>=0.11.13
